argila/__init__.py
argila/exceptions.py
src/__init__.py
src/argila.py
src/exceptions.py
argilaparser-2.0.1.dist-info/LICENSE
argilaparser-2.0.1.dist-info/METADATA
argilaparser-2.0.1.dist-info/WHEEL
argilaparser-2.0.1.dist-info/top_level.txt
argilaparser-2.0.1.dist-info/RECORD
