Metadata-Version: 2.1
Name: argilaparser
Version: 2.0.1
Summary: A lightweight object oriented lib for Python 3.8+ to help create CLI programs more easily. It has an elegant design taking advantage of built-in modules, and delivering a conducive environment to fast development and readability.
Home-page: https://github.com/d4sein/Argila-Parser
Author: d4sein
Author-email: williann.nasc@gmail.com
License: UNKNOWN
Platform: UNKNOWN
Classifier: Programming Language :: Python :: 3
Classifier: License :: OSI Approved :: MIT License
Classifier: Operating System :: OS Independent
Requires-Python: >=3.8
